{"createTime":1547887259866,"dataType":1101,"dealResult":1,"id":"2f3807370c5246f3a7f2b5baa803751e","jsonData":"{\"agentId\":\"0056d0734ce04769a4eafc6175017402\",\"applyDate\":\"2019-01-18 19:08:39\",\"applySource\":0,\"deliverDate\":\"2019-01-18 19:07:33\",\"districtId\":\"330106\",\"earlywarningDate\":\"2019-01-18 19:08:39\",\"getterId\":\"6539abb02dcf479db9f3a27161188c5c\",\"id\":\"39cfb2e11c1d4b4289f873e5f0b9b404\",\"isApply\":true,\"isChipseal\":false,\"isDeliver\":true,\"isEarlywarning\":true,\"isLogout\":true,\"isLoss\":false,\"isMake\":true,\"isPass\":false,\"isPersonal\":false,\"isRecord\":true,\"isUndertake\":true,\"logoutDate\":\"2019-01-19 16:40:59\",\"logoutPersonId\":\"a90b271fb338413b8c080dbb89e2a398\",\"loss\":false,\"makeDate\":\"2019-01-18 19:02:59\",\"makeDepartmentCode\":\"91370112MA3C8UQK8G\",\"makeDepartmentName\":\"方文刻章店\",\"materialsCode\":\"01\",\"mimeographDescription\":\"01\",\"recordDate\":\"2019-01-18 18:58:49\",\"recordDepartmentCode\":\"HZSXHFJ\",\"recordDepartmentName\":\"杭州市西湖分局\",\"sealCenterImage\":\"01\",\"sealCode\":\"33010606000323\",\"sealMakeTypeCode\":\"01\",\"sealName\":\"杭州海量信息技术有限公司\",\"sealReason\":\"01\",\"sealShapeCode\":\"01\",\"sealSize\":\"20*20\",\"sealStatusCode\":\"06\",\"sealTypeCode\":\"04\",\"undertakeDate\":\"2019-01-18 18:58:49\",\"useDepartmentCode\":\"913301067272207765\",\"useDepartmentName\":\"杭州海量信息技术有限公司\"}","operateType":15}